nesteddict/__init__.py
nesteddict/base.py
nestict-0.1.0.dist-info/LICENSE
nestict-0.1.0.dist-info/METADATA
nestict-0.1.0.dist-info/WHEEL
nestict-0.1.0.dist-info/top_level.txt
nestict-0.1.0.dist-info/RECORD
